stucent/__init__.py
stucent/client.py
stucent/config.py
stucent/content_tree.py
stucent/models.py
stucent/services.py
Stucent-0.1.7.dist-info/LICENSE
Stucent-0.1.7.dist-info/METADATA
Stucent-0.1.7.dist-info/WHEEL
Stucent-0.1.7.dist-info/top_level.txt
Stucent-0.1.7.dist-info/RECORD
