Metadata-Version: 2.1
Name: Stucent
Version: 0.1.7
License-File: LICENSE
Requires-Dist: requests ==2.31.0
Requires-Dist: pydantic ==2.6.1
Requires-Dist: python-dotenv ==1.0.1
